{
  "project_info": {
    "project_number": "451783298102",
    "project_id": "fluttersigninfc",
    "storage_bucket": "fluttersigninfc.appspot.com"
  },
  "client": [
    {
      "client_info": {
        "mobilesdk_app_id": "1:451783298102:android:7c925485b9aba09559dc97",
        "android_client_info": {
          "package_name": "com.example.food_delivery_app"
        }
      },
      "oauth_client": [
        {
          "client_id": "451783298102-7sb59cf8kjltm8uthoh94kblv8hcik1l.apps.googleusercontent.com",
          "client_type": 1,
          "android_info": {
            "package_name": "com.example.food_delivery_app",
            "certificate_hash": "ae9dc1afd0e6cac3973c0895cd6289cfee45effc"
          }
        },
        {
          "client_id": "451783298102-n2t1pvf2aha5hsnb43ap51rqp8sf1i71.apps.googleusercontent.com",
          "client_type": 1,
          "android_info": {
            "package_name": "com.example.food_delivery_app",
            "certificate_hash": "077ab48660515a6b493be02280631633361952ed"
          }
        },
        {
          "client_id": "451783298102-k1ek2ulko131p0b9khvi6bi3tm3foom2.apps.googleusercontent.com",
          "client_type": 3
        }
      ],
      "api_key": [
        {
          "current_key": "AIzaSyDe-4gFQINLd10yXe5PazcvGgqZhD-jHA0"
        }
      ],
      "services": {
        "appinvite_service": {
          "other_platform_oauth_client": [
            {
              "client_id": "451783298102-k1ek2ulko131p0b9khvi6bi3tm3foom2.apps.googleusercontent.com",
              "client_type": 3
            },
            {
              "client_id": "451783298102-bs80miq6vonkjmmfsprjirjhu1n04vu1.apps.googleusercontent.com",
              "client_type": 2,
              "ios_info": {
                "bundle_id": "com.example.foodDeliveryApp"
              }
            }
          ]
        }
      }
    }
  ],
  "configuration_version": "1"
}